odoo/addons/company_country/README.rst
odoo/addons/company_country/__init__.py
odoo/addons/company_country/__manifest__.py
odoo/addons/company_country/data/res_config.xml
odoo/addons/company_country/i18n/company_country.pot
odoo/addons/company_country/models/__init__.py
odoo/addons/company_country/models/res_config.py
odoo/addons/company_country/readme/CONFIGURE.rst
odoo/addons/company_country/readme/CONTRIBUTORS.rst
odoo/addons/company_country/readme/CREDITS.rst
odoo/addons/company_country/readme/DESCRIPTION.rst
odoo/addons/company_country/readme/INSTALL.rst
odoo/addons/company_country/readme/USAGE.rst
odoo/addons/company_country/static/description/icon.png
odoo/addons/company_country/static/description/index.html
odoo/addons/company_country/tests/__init__.py
odoo/addons/company_country/tests/test_company_country.py
odoo11_addon_company_country-11.0.1.0.0.99.dev7.dist-info/METADATA
odoo11_addon_company_country-11.0.1.0.0.99.dev7.dist-info/WHEEL
odoo11_addon_company_country-11.0.1.0.0.99.dev7.dist-info/top_level.txt
odoo11_addon_company_country-11.0.1.0.0.99.dev7.dist-info/RECORD
